{
  "update_time": "2026-07-09 16:34:05",
  "sources": {
    "微博": {
      "topics": [],
      "count": 0,
      "status": "empty"
    },
    "百度": {
      "topics": [],
      "count": 0,
      "status": "empty"
    },
    "B站": {
      "topics": [],
      "count": 0,
      "status": "empty"
    },
    "知乎": {
      "topics": [],
      "count": 0,
      "status": "empty"
    },
    "抖音": {
      "topics": [],
      "count": 0,
      "status": "empty"
    },
    "虎扑": {
      "topics": [
        {
          "title": "奥莱：阿根廷心中超越卫冕的信念，是让梅西的绝唱更晚到来",
          "url": "https://soccer.hupu.com/",
          "hot": ""
        },
        {
          "title": "20年前的今天，意大利击败法国，第4次捧起世界杯冠军",
          "url": "https://soccer.hupu.com/",
          "hot": ""
        },
        {
          "title": "跟队：桑托斯内部认为内马尔不会留队，他更可能去海外发展",
          "url": "https://soccer.hupu.com/",
          "hot": ""
        },
        {
          "title": "前教练：萨卡速度更快踢得更直接，昆达的内切可能更出色",
          "url": "https://soccer.hupu.com/",
          "hot": ""
        },
        {
          "title": "西甲球员世界杯1/8决赛最佳阵容：姆巴佩、贝林厄姆领衔",
          "url": "https://soccer.hupu.com/",
          "hot": ""
        },
        {
          "title": "巴拉圭人街头焚烧“姆巴佩玩偶”，目的是给他带去厄运",
          "url": "https://soccer.hupu.com/",
          "hot": ""
        },
        {
          "title": "法国发布1/4决赛对阵摩洛哥海报，姆巴佩/登贝莱/奥利塞出镜",
          "url": "https://soccer.hupu.com/",
          "hot": ""
        },
        {
          "title": "葡萄牙本届世界杯边卫创造6次得分良机，而中场只创造3次",
          "url": "https://soccer.hupu.com/",
          "hot": ""
        },
        {
          "title": "C罗不是曼联第一人？甚至可以说是英超第一人",
          "url": "https://soccer.hupu.com/",
          "hot": ""
        },
        {
          "title": "超过70名欧洲议员呼吁对国际足联及其主席因凡蒂诺展开调查",
          "url": "https://soccer.hupu.com/",
          "hot": ""
        }
      ],
      "count": 10,
      "status": "success"
    },
    "懂球帝": {
      "topics": [
        {
          "title": "西甲官方晒世界杯16强西甲最佳阵：姆巴佩、费兰、贝林在列",
          "url": "https://www.dongqiudi.com/",
          "hot": ""
        },
        {
          "title": "全市场：意甲新赛季裁判更接近欧足联标准",
          "url": "https://www.dongqiudi.com/",
          "hot": ""
        },
        {
          "title": "达曼协作门将：不应比较梅罗，两年后梅西是否还在踢还很难说",
          "url": "https://www.dongqiudi.com/",
          "hot": ""
        }
      ],
      "count": 3,
      "status": "success"
    },
    "小红书": {
      "topics": [],
      "count": 0,
      "status": "empty"
    },
    "咪咕": {
      "topics": [],
      "count": 0,
      "status": "empty"
    },
    "网易": {
      "topics": [
        {
          "title": "法国3人领跑FIFA3大实力榜：姆巴佩进攻第1 力压梅西",
          "url": "https://sports.163.com/worldcup2026/",
          "hot": ""
        },
        {
          "title": "葡萄牙出局后，C罗首次更新个人社媒：永远的葡萄牙",
          "url": "https://sports.163.com/worldcup2026/",
          "hot": ""
        },
        {
          "title": "让二追三!阿根廷3-2绝境逆转埃及进8强 恩佐绝杀",
          "url": "https://sports.163.com/worldcup2026/",
          "hot": ""
        },
        {
          "title": "埃及足协向国际足联提出申诉，指责裁判导致其世界杯出局",
          "url": "https://sports.163.com/worldcup2026/",
          "hot": ""
        },
        {
          "title": "世界杯被淘汰队伍排名：巴西第11平队史第二差，C罗第13",
          "url": "https://sports.163.com/worldcup2026/",
          "hot": ""
        },
        {
          "title": "密友证实！34岁内马尔考虑退役，不满多年来遭巴西公众不公平对待",
          "url": "https://sports.163.com/worldcup2026/",
          "hot": ""
        },
        {
          "title": "裁判界的GOAT！66岁名哨怒斥埃及：没人能质疑世界杯执法的公正性",
          "url": "https://sports.163.com/worldcup2026/",
          "hot": ""
        },
        {
          "title": "世界杯出局40队排名确定 巴西历史第2差 葡萄牙第13 亚洲新军垫底",
          "url": "https://sports.163.com/worldcup2026/",
          "hot": ""
        },
        {
          "title": "摩洛哥队主帅：世界杯夺冠，是我们的唯一目标",
          "url": "https://sports.163.com/worldcup2026/",
          "hot": ""
        },
        {
          "title": "世界杯官方晒数据：场均观众超6.5万，上座率99.7%",
          "url": "https://sports.163.com/worldcup2026/",
          "hot": ""
        },
        {
          "title": "FIFA官方：贾斯汀-比伯将担任世界杯决赛中场秀表演嘉宾",
          "url": "https://sports.163.com/worldcup2026/",
          "hot": ""
        }
      ],
      "count": 11,
      "status": "success"
    },
    "腾讯": {
      "topics": [],
      "count": 0,
      "status": "empty"
    }
  }
}