{
  "update_time": "2026-06-30 22:36:00",
  "sources": {
    "微博": {
      "topics": [
        {
          "title": "乒乓球收视率远不及世界杯",
          "url": "https://s.weibo.com/weibo?q=%E4%B9%92%E4%B9%93%E7%90%83%E6%94%B6%E8%A7%86%E7%8E%87%E8%BF%9C%E4%B8%8D%E5%8F%8A%E4%B8%96%E7%95%8C%E6%9D%AF",
          "hot": 0,
          "label": ""
        }
      ],
      "count": 1,
      "status": "success"
    },
    "百度": {
      "topics": [],
      "count": 0,
      "status": "empty"
    },
    "B站": {
      "topics": [],
      "count": 0,
      "status": "empty"
    },
    "知乎": {
      "topics": [],
      "count": 0,
      "status": "empty"
    },
    "抖音": {
      "topics": [
        {
          "title": "内马尔安慰日本球员",
          "url": "https://www.douyin.com/search/%E5%86%85%E9%A9%AC%E5%B0%94%E5%AE%89%E6%85%B0%E6%97%A5%E6%9C%AC%E7%90%83%E5%91%98",
          "hot": "773.8万"
        }
      ],
      "count": 1,
      "status": "success"
    },
    "虎扑": {
      "topics": [
        {
          "title": "基米希vs巴拉圭完成103次向前传球，为本届赛事单场之最",
          "url": "https://soccer.hupu.com/",
          "hot": ""
        },
        {
          "title": "世界杯历史进球榜：巴西246球领先德国3球，阿根廷160球",
          "url": "https://soccer.hupu.com/",
          "hot": ""
        },
        {
          "title": "卡尔：错过世界杯最初几天很难熬，家人和拜仁给了我力量",
          "url": "https://soccer.hupu.com/",
          "hot": ""
        },
        {
          "title": "意西德最近1次世界杯冠军后，至今都未赢得过1场淘汰赛",
          "url": "https://soccer.hupu.com/",
          "hot": ""
        },
        {
          "title": "[流言板]外界批评罗德里？佩德里：我们这里没有其他人拿过金球奖",
          "url": "https://soccer.hupu.com/",
          "hot": ""
        }
      ],
      "count": 5,
      "status": "success"
    },
    "懂球帝": {
      "topics": [
        {
          "title": "四年之约，你还记得当时的约定吗？快来重温当年的世界杯祈愿",
          "url": "https://www.dongqiudi.com/",
          "hot": ""
        },
        {
          "title": "库库：世界杯想和姆巴佩换球衣；如果可以想为皇马签下罗德里",
          "url": "https://www.dongqiudi.com/",
          "hot": ""
        },
        {
          "title": "库库：恩佐祝贺了我，若他真的加盟皇马我非常欢迎",
          "url": "https://www.dongqiudi.com/",
          "hot": ""
        },
        {
          "title": "TA：德国自夺得巴西世界杯后便跌入谷底，如今需要新一轮改革",
          "url": "https://www.dongqiudi.com/",
          "hot": ""
        },
        {
          "title": "前巴西国脚嘲讽德佩：为世界杯留力，如今又为科林蒂安留力了",
          "url": "https://www.dongqiudi.com/",
          "hot": ""
        }
      ],
      "count": 5,
      "status": "success"
    },
    "小红书": {
      "topics": [],
      "count": 0,
      "status": "empty"
    },
    "咪咕": {
      "topics": [],
      "count": 0,
      "status": "empty"
    },
    "网易": {
      "topics": [
        {
          "title": "德国点球大战4-5巴拉圭 连续3届世界杯无缘16强",
          "url": "https://sports.163.com/worldcup2026/",
          "hot": ""
        },
        {
          "title": "世界杯：荷兰点球3-4无缘16强！创队史最差战绩 摩洛哥踢加拿大",
          "url": "https://sports.163.com/worldcup2026/",
          "hot": ""
        },
        {
          "title": "耻辱！德国前18次世界杯4冠4亚4季17次八强，近三届无缘16强",
          "url": "https://sports.163.com/worldcup2026/",
          "hot": ""
        },
        {
          "title": "感谢德国队！巴拉圭全国放假一天，德国本届世界杯第2次送假期",
          "url": "https://sports.163.com/worldcup2026/",
          "hot": ""
        },
        {
          "title": "巴拉圭队长：我们配得上留在世界杯中；很难形容现在的心情",
          "url": "https://sports.163.com/worldcup2026/",
          "hot": ""
        },
        {
          "title": "世界杯-巴西2-1逆转日本 马丁内利96分钟绝杀",
          "url": "https://sports.163.com/worldcup2026/",
          "hot": ""
        },
        {
          "title": "世界杯16强已定4席 2场点球战+荷兰德国出局 1/8决赛首组对决确定",
          "url": "https://sports.163.com/worldcup2026/",
          "hot": ""
        }
      ],
      "count": 7,
      "status": "success"
    },
    "腾讯": {
      "topics": [],
      "count": 0,
      "status": "empty"
    }
  }
}