{
  "update_time": "2026-07-12 23:05:06",
  "sources": {
    "微博": {
      "topics": [
        {
          "title": "樊振东将解说世界杯决赛",
          "url": "https://s.weibo.com/weibo?q=%E6%A8%8A%E6%8C%AF%E4%B8%9C%E5%B0%86%E8%A7%A3%E8%AF%B4%E4%B8%96%E7%95%8C%E6%9D%AF%E5%86%B3%E8%B5%9B",
          "hot": 0,
          "label": ""
        },
        {
          "title": "鹿晗意外英格兰还留在世界杯",
          "url": "https://s.weibo.com/weibo?q=%E9%B9%BF%E6%99%97%E6%84%8F%E5%A4%96%E8%8B%B1%E6%A0%BC%E5%85%B0%E8%BF%98%E7%95%99%E5%9C%A8%E4%B8%96%E7%95%8C%E6%9D%AF",
          "hot": 0,
          "label": ""
        }
      ],
      "count": 2,
      "status": "success"
    },
    "百度": {
      "topics": [],
      "count": 0,
      "status": "empty"
    },
    "B站": {
      "topics": [
        {
          "title": "王冰冰小布聊世界杯争议名场面",
          "url": "https://search.bilibili.com/all?keyword=%E7%8E%8B%E5%86%B0%E5%86%B0%E5%B0%8F%E5%B8%83%E8%81%8A%E4%B8%96%E7%95%8C%E6%9D%AF%E4%BA%89%E8%AE%AE%E5%90%8D%E5%9C%BA%E9%9D%A2",
          "hot": 0
        }
      ],
      "count": 1,
      "status": "success"
    },
    "知乎": {
      "topics": [],
      "count": 0,
      "status": "empty"
    },
    "抖音": {
      "topics": [
        {
          "title": "世界前四齐聚世界杯四强",
          "url": "https://www.douyin.com/search/%E4%B8%96%E7%95%8C%E5%89%8D%E5%9B%9B%E9%BD%90%E8%81%9A%E4%B8%96%E7%95%8C%E6%9D%AF%E5%9B%9B%E5%BC%BA",
          "hot": "853.3万"
        }
      ],
      "count": 1,
      "status": "success"
    },
    "虎扑": {
      "topics": [
        {
          "title": "贝克汉姆Ins：英格兰队挺进世界杯半决赛，我深感自豪",
          "url": "https://soccer.hupu.com/",
          "hot": ""
        },
        {
          "title": "Opta：小蜘蛛在世界杯打进5球，其中4球出现在淘汰赛",
          "url": "https://soccer.hupu.com/",
          "hot": ""
        },
        {
          "title": "世界杯1/4决赛过人榜：多库、欧纳希、梅西5次并列居首",
          "url": "https://soccer.hupu.com/",
          "hot": ""
        },
        {
          "title": "[流言板]B费Ins晒卢克-肖童年照为其31岁庆生：生日快乐，我的男孩",
          "url": "https://soccer.hupu.com/",
          "hot": ""
        },
        {
          "title": "阿尔瓦雷斯踢的差是因为这届阿根廷没有边锋给他拉空间，边锋是真的过于拉胯，阿根廷一场都创造不出来几次射门机会，全是落位进攻，一进球就想猥琐防守，守又守不住",
          "url": "https://soccer.hupu.com/",
          "hot": ""
        },
        {
          "title": "不吐不快，为什么葡萄牙不管赢还是输，全在嘲讽c罗，到底是哪个群体",
          "url": "https://soccer.hupu.com/",
          "hot": ""
        },
        {
          "title": "蓝白过去13场世界杯比赛详情",
          "url": "https://soccer.hupu.com/",
          "hot": ""
        }
      ],
      "count": 7,
      "status": "success"
    },
    "懂球帝": {
      "topics": [
        {
          "title": "记者：皇马盼续约维尼修斯，但不接受2000万欧年薪要价",
          "url": "https://www.dongqiudi.com/",
          "hot": ""
        },
        {
          "title": "皮尔斯：拉什福德连续两场未登场，图赫尔训练发现何因？",
          "url": "https://www.dongqiudi.com/",
          "hot": ""
        }
      ],
      "count": 2,
      "status": "success"
    },
    "小红书": {
      "topics": [],
      "count": 0,
      "status": "empty"
    },
    "咪咕": {
      "topics": [],
      "count": 0,
      "status": "empty"
    },
    "网易": {
      "topics": [
        {
          "title": "世界杯-阿根廷3-1瑞士进4强 小蜘蛛劳塔罗加时破门",
          "url": "https://sports.163.com/worldcup2026/",
          "hot": ""
        },
        {
          "title": "三英战吕布！FIFA前4名包揽世界杯4强：西班牙VS法国 英格兰VS阿根廷",
          "url": "https://sports.163.com/worldcup2026/",
          "hot": ""
        },
        {
          "title": "中国足协：傅明执法7场世界杯，中国裁判首进淘汰赛",
          "url": "https://sports.163.com/worldcup2026/",
          "hot": ""
        },
        {
          "title": "世界杯夺冠概率更新：法国继续领跑，西英阿分列二三四名",
          "url": "https://sports.163.com/worldcup2026/",
          "hot": ""
        },
        {
          "title": "英格兰加时2-1挪威晋级四强 贝林厄姆连场双响",
          "url": "https://sports.163.com/worldcup2026/",
          "hot": ""
        },
        {
          "title": "世界杯突发悲剧！25岁南非国脚上吊自杀",
          "url": "https://sports.163.com/worldcup2026/",
          "hot": ""
        },
        {
          "title": "39岁高龄的梅西，是如何重新变成右边锋的？",
          "url": "https://sports.163.com/worldcup2026/",
          "hot": ""
        },
        {
          "title": "世界杯射手榜：姆巴佩梅西8球，贝林、凯恩6球，登贝莱5球",
          "url": "https://sports.163.com/worldcup2026/",
          "hot": ""
        },
        {
          "title": "哈兰德告别世界杯！本届首次哑火+全场仅2射，犯规致队友进球取消",
          "url": "https://sports.163.com/worldcup2026/",
          "hot": ""
        }
      ],
      "count": 9,
      "status": "success"
    },
    "腾讯": {
      "topics": [],
      "count": 0,
      "status": "empty"
    }
  }
}